pyobscenity/__init__.py
pyobscenity/censor.py
pyobscenity/dataset.py
pyobscenity/english_preset.py
pyobscenity/matcher.py
pyobscenity/pattern.py
pyobscenity/transformers.py
pyobscenity/util.py
pyobscenity-0.1.0.dist-info/METADATA
pyobscenity-0.1.0.dist-info/WHEEL
pyobscenity-0.1.0.dist-info/licenses/LICENSE
pyobscenity-0.1.0.dist-info/RECORD
