Metadata-Version: 2.4
Name: pyobscenity
Version: 0.1.0
Summary: Python port of the Obscenity profanity filtering library
Project-URL: Homepage, https://github.com/gsteinLTU/pyobscenity
Project-URL: Source, https://github.com/gsteinLTU/pyobscenity
Author-email: Gordon Stein <gstein@ltu.edu>
License: MIT
License-File: LICENSE
Requires-Python: >=3.12
Requires-Dist: regex>=2025.11.3
Provides-Extra: dev
Requires-Dist: mypy>=1.19.0; extra == 'dev'
Requires-Dist: pytest-cov>=7.0.0; extra == 'dev'
Requires-Dist: pytest>=9.0.1; extra == 'dev'
Requires-Dist: ruff>=0.14.7; extra == 'dev'
